{"cameraMode":{"drawMode":0,"name":"Shaded","section":"Shading Mode"},"sceneLighting":true,"audioPlay":false,"sceneViewState":{"m_AlwaysRefresh":false,"showFog":true,"showSkybox":true,"showFlares":true,"showImageEffects":true,"showParticleSystems":true,"showVisualEffectGraphs":true,"m_FxEnabled":true},"in2DMode":false,"pivot":{"x":-2566.6171875,"y":35.852210998535159,"z":-252.45309448242188},"rotation":{"x":-0.06582227349281311,"y":-0.6808468103408814,"z":0.06165429949760437,"w":-0.726868748664856},"size":2.3085429668426515,"orthographic":false}